{
    "season": "2018",
    "matches": [
        {
            "date": "2018-12-29",
            "opponent": "FC 오리너스",
            "result": "win",
            "score": "8:3",
            "mvp": "박윤제"
        },
        {
            "date": "2018-12-23",
            "opponent": "GPS",
            "result": "loss",
            "score": "0:3",
            "mvp": "이치석"
        },
        {
            "date": "2018-12-16",
            "opponent": "위너스 FC",
            "result": "win",
            "score": "7:3",
            "mvp": "윤종진"
        },
        {
            "date": "2018-12-09",
            "opponent": "광림FC",
            "result": "loss",
            "score": "4:5",
            "mvp": "이상보"
        },
        {
            "date": "2018-12-02",
            "opponent": "인터블루",
            "result": "loss",
            "score": "5:12",
            "mvp": "윤종진"
        },
        {
            "date": "2018-11-25",
            "opponent": "도우리",
            "result": "win",
            "score": "10:3",
            "mvp": "이정호"
        },
        {
            "date": "2018-11-18",
            "opponent": "궁동 FC",
            "result": "win",
            "score": "9:1",
            "mvp": "김진호"
        },
        {
            "date": "2018-11-11",
            "opponent": "FC빈체로",
            "result": "win",
            "score": "5:4",
            "mvp": "반기훈"
        },
        {
            "date": "2018-11-04",
            "opponent": "조원FC",
            "result": "win",
            "score": "5:0",
            "mvp": "안창영"
        },
        {
            "date": "2018-11-04",
            "opponent": "남우FC",
            "result": "win",
            "score": "9:1",
            "mvp": "반기훈"
        },
        {
            "date": "2018-10-27",
            "opponent": "동대문구청동호회",
            "result": "loss",
            "score": "2:4",
            "mvp": "김태종"
        },
        {
            "date": "2018-10-21",
            "opponent": "해날FC",
            "result": "win",
            "score": "8:1",
            "mvp": "조상현"
        },
        {
            "date": "2018-10-14",
            "opponent": "Maestro",
            "result": "loss",
            "score": "3:7",
            "mvp": "이정호"
        },
        {
            "date": "2018-10-07",
            "opponent": "SM FC",
            "result": "win",
            "score": "10:1",
            "mvp": "김장훈"
        },
        {
            "date": "2018-09-30",
            "opponent": "세운FC",
            "result": "win",
            "score": "5:1",
            "mvp": "안태수"
        },
        {
            "date": "2018-09-16",
            "opponent": "Eleven",
            "result": "win",
            "score": "4:2",
            "mvp": "유지현"
        },
        {
            "date": "2018-09-09",
            "opponent": "Monster F.C",
            "result": "loss",
            "score": "3:10",
            "mvp": "이정호"
        },
        {
            "date": "2018-09-02",
            "opponent": "팀독",
            "result": "win",
            "score": "6:4",
            "mvp": "이항규"
        },
        {
            "date": "2018-08-26",
            "opponent": "NB",
            "result": "win",
            "score": "8:3",
            "mvp": "안창영"
        },
        {
            "date": "2018-08-19",
            "opponent": "FC FEEL",
            "result": "win",
            "score": "7:2",
            "mvp": "강재웅"
        },
        {
            "date": "2018-08-05",
            "opponent": "P.O.S",
            "result": "draw",
            "score": "3:3",
            "mvp": "이항규"
        },
        {
            "date": "2018-07-29",
            "opponent": "FC Village",
            "result": "win",
            "score": "6:4",
            "mvp": "이항규"
        },
        {
            "date": "2018-07-22",
            "opponent": "Maestro",
            "result": "win",
            "score": "7:5",
            "mvp": "안창영"
        },
        {
            "date": "2018-07-15",
            "opponent": "FC 강북",
            "result": "win",
            "score": "6:4",
            "mvp": "이치석"
        },
        {
            "date": "2018-07-08",
            "opponent": "피케이",
            "result": "win",
            "score": "4:0",
            "mvp": "서원덕"
        },
        {
            "date": "2018-06-24",
            "opponent": "레인저",
            "result": "win",
            "score": "7:3",
            "mvp": "이정호"
        },
        {
            "date": "2018-06-24",
            "opponent": "라온 FC",
            "result": "win",
            "score": "4:2",
            "mvp": "권창호"
        },
        {
            "date": "2018-06-17",
            "opponent": "우리 FC",
            "result": "win",
            "score": "6:1",
            "mvp": "오진석"
        },
        {
            "date": "2018-06-17",
            "opponent": "보라매 FC",
            "result": "draw",
            "score": "1:1",
            "mvp": "반기훈"
        },
        {
            "date": "2018-06-10",
            "opponent": "선후FC",
            "result": "win",
            "score": "5:4",
            "mvp": "이항규"
        },
        {
            "date": "2018-06-03",
            "opponent": "FC Return",
            "result": "win",
            "score": "8:4",
            "mvp": "이정호"
        },
        {
            "date": "2018-05-26",
            "opponent": "FC그래프트",
            "result": "win",
            "score": "3:1",
            "mvp": "이항규"
        },
        {
            "date": "2018-05-20",
            "opponent": "회기FC",
            "result": "win",
            "score": "6:1",
            "mvp": "박윤제"
        },
        {
            "date": "2018-05-12",
            "opponent": "YOS",
            "result": "loss",
            "score": "5:10",
            "mvp": "우희헌"
        },
        {
            "date": "2018-05-06",
            "opponent": "무명FC",
            "result": "win",
            "score": "11:0",
            "mvp": "강재웅"
        },
        {
            "date": "2018-04-29",
            "opponent": "FC GO",
            "result": "win",
            "score": "8:1",
            "mvp": "유지현"
        },
        {
            "date": "2018-04-22",
            "opponent": "방화3동 조기축구회",
            "result": "loss",
            "score": "3:5",
            "mvp": "박윤제"
        },
        {
            "date": "2018-04-15",
            "opponent": "E1 FC",
            "result": "win",
            "score": "4:3",
            "mvp": "박지성"
        },
        {
            "date": "2018-04-08",
            "opponent": "E.S. Falcon",
            "result": "loss",
            "score": "6:10",
            "mvp": "임태현"
        },
        {
            "date": "2018-04-01",
            "opponent": "FC.Tempo",
            "result": "win",
            "score": "6:0",
            "mvp": "조상현"
        },
        {
            "date": "2018-03-24",
            "opponent": "동대문구청동호회",
            "result": "draw",
            "score": "6:6",
            "mvp": "윤종진"
        },
        {
            "date": "2018-03-18",
            "opponent": "FC뉴클리어",
            "result": "loss",
            "score": "0:2",
            "mvp": "유지현"
        },
        {
            "date": "2018-03-11",
            "opponent": "FC 아우토반",
            "result": "loss",
            "score": "3:4",
            "mvp": "김장훈"
        },
        {
            "date": "2018-03-04",
            "opponent": "성균관대방송국팀",
            "result": "loss",
            "score": "4:5",
            "mvp": "조상현"
        },
        {
            "date": "2018-02-24",
            "opponent": "허리케인FC",
            "result": "loss",
            "score": "5:7",
            "mvp": "이정호"
        },
        {
            "date": "2018-02-11",
            "opponent": "맨땅축구클럽",
            "result": "win",
            "score": "5:1",
            "mvp": "조상현"
        },
        {
            "date": "2018-02-04",
            "opponent": "FC한",
            "result": "win",
            "score": "4:3",
            "mvp": "이정호"
        },
        {
            "date": "2018-01-28",
            "opponent": "FC EXIT",
            "result": "win",
            "score": "7:5",
            "mvp": "이정호"
        },
        {
            "date": "2018-01-21",
            "opponent": "FC615",
            "result": "win",
            "score": "7:4",
            "mvp": "박윤제"
        },
        {
            "date": "2018-01-14",
            "opponent": "FC시스템",
            "result": "draw",
            "score": "5:5",
            "mvp": "윤종진"
        },
        {
            "date": "2018-01-07",
            "opponent": "TAF",
            "result": "win",
            "score": "5:0",
            "mvp": "강재웅"
        }
    ],
    "players": {
        "박지성": {
            "appearances": 38,
            "goals": 0,
            "mvp": 1
        },
        "고태경": {
            "appearances": 10,
            "goals": 1,
            "mvp": 0
        },
        "윤호진": {
            "appearances": 0,
            "goals": 0,
            "mvp": 0
        },
        "김기호": {
            "appearances": 3,
            "goals": 0,
            "mvp": 0
        },
        "김진호": {
            "appearances": 16,
            "goals": 8,
            "mvp": 1
        },
        "김영주": {
            "appearances": 8,
            "goals": 0,
            "mvp": 1
        },
        "이항규": {
            "appearances": 44,
            "goals": 48,
            "mvp": 3
        },
        "강용기": {
            "appearances": 14,
            "goals": 0,
            "mvp": 0
        },
        "김경배": {
            "appearances": 0,
            "goals": 0,
            "mvp": 0
        },
        "권창호": {
            "appearances": 29,
            "goals": 17,
            "mvp": 1
        },
        "강재웅": {
            "appearances": 13,
            "goals": 4,
            "mvp": 1
        },
        "조상현": {
            "appearances": 19,
            "goals": 16,
            "mvp": 3
        },
        "반기훈": {
            "appearances": 40,
            "goals": 17,
            "mvp": 1
        },
        "윤정광": {
            "appearances": 1,
            "goals": 0,
            "mvp": 0
        },
        "오태균": {
            "appearances": 0,
            "goals": 0,
            "mvp": 0
        },
        "김장훈": {
            "appearances": 4,
            "goals": 6,
            "mvp": 1
        },
        "김병태": {
            "appearances": 10,
            "goals": 0,
            "mvp": 0
        },
        "안태수": {
            "appearances": 23,
            "goals": 3,
            "mvp": 1
        },
        "안창영": {
            "appearances": 22,
            "goals": 10,
            "mvp": 2
        },
        "김종우": {
            "appearances": 0,
            "goals": 0,
            "mvp": 0
        },
        "장상우": {
            "appearances": 0,
            "goals": 0,
            "mvp": 0
        },
        "윤종진": {
            "appearances": 34,
            "goals": 30,
            "mvp": 2
        },
        "박윤제": {
            "appearances": 16,
            "goals": 1,
            "mvp": 1
        },
        "우희헌": {
            "appearances": 23,
            "goals": 1,
            "mvp": 1
        },
        "유지현": {
            "appearances": 32,
            "goals": 3,
            "mvp": 2
        },
        "임태현": {
            "appearances": 25,
            "goals": 7,
            "mvp": 1
        },
        "이치석": {
            "appearances": 23,
            "goals": 0,
            "mvp": 1
        },
        "서원덕": {
            "appearances": 12,
            "goals": 0,
            "mvp": 1
        },
        "김동규": {
            "appearances": 4,
            "goals": 1,
            "mvp": 0
        },
        "하승협": {
            "appearances": 0,
            "goals": 0,
            "mvp": 0
        },
        "이정호": {
            "appearances": 33,
            "goals": 50,
            "mvp": 4
        },
        "안수영": {
            "appearances": 0,
            "goals": 0,
            "mvp": 0
        },
        "김동후": {
            "appearances": 4,
            "goals": 0,
            "mvp": 0
        },
        "이광수": {
            "appearances": 0,
            "goals": 0,
            "mvp": 0
        },
        "안태수": {
            "appearances": 23,
            "goals": 3,
            "mvp": 0
        },
        "오진석": {
            "appearances": 14,
            "goals": 19,
            "mvp": 1
        },
        "김명재": {
            "appearances": 15,
            "goals": 0,
            "mvp": 1
        },
        "김성광": {
            "appearances": 3,
            "goals": 0,
            "mvp": 0
        },
        "김태종": {
            "appearances": 3,
            "goals": 3,
            "mvp": 1
        },
        "이상보": {
            "appearances": 3,
            "goals": 0,
            "mvp": 1
        }
    }
}